pycep/__init__.py
pycep/adapters/__init__.py
pycep/adapters/aiohttp_client.py
pycep/adapters/http_response.py
pycep/adapters/httpx_client.py
pycep/cep_data.py
pycep/cep_service_loader.py
pycep/protocols/__init__.py
pycep/protocols/http_client.py
pycep/protocols/query_service.py
pycep/protocols/service_loader.py
pycep/pycep.py
pycep/services/__init__.py
pycep/services/apicep.py
pycep/services/brasilapi.py
pycep/services/opencep.py
pycep/services/viacep.py
pycep-1.0.4.dist-info/LICENSE.md
pycep-1.0.4.dist-info/METADATA
pycep-1.0.4.dist-info/WHEEL
pycep-1.0.4.dist-info/RECORD
