Metadata-Version: 2.1
Name: pycep
Version: 1.0.4
Summary: Consulta CEPs em vários serviços (Correios, ViaCep, OpenCep) de maneira totalmente assíncrona
Home-page: https://github.com/erickod/pycep
Author: Erick Duarte
Author-email: erickod@gmail.com
Requires-Python: >=3.10
Classifier: Programming Language :: Python :: 3
Classifier: Programming Language :: Python :: 3.10
Classifier: Programming Language :: Python :: 3.11
Classifier: Programming Language :: Python :: 3.12
Requires-Dist: aiohttp (>=3.10.10,<4.0.0)
Requires-Dist: httpx (>=0.27.2,<0.28.0)
Project-URL: Repository, https://github.com/erickod/pycep
